klu_sdk/__init__.py
klu_sdk/_base_client.py
klu_sdk/_client.py
klu_sdk/_compat.py
klu_sdk/_constants.py
klu_sdk/_exceptions.py
klu_sdk/_files.py
klu_sdk/_models.py
klu_sdk/_qs.py
klu_sdk/_resource.py
klu_sdk/_response.py
klu_sdk/_streaming.py
klu_sdk/_types.py
klu_sdk/_version.py
klu_sdk/py.typed
klu_sdk/_utils/__init__.py
klu_sdk/_utils/_logs.py
klu_sdk/_utils/_proxy.py
klu_sdk/_utils/_reflection.py
klu_sdk/_utils/_streams.py
klu_sdk/_utils/_sync.py
klu_sdk/_utils/_transform.py
klu_sdk/_utils/_typing.py
klu_sdk/_utils/_utils.py
klu_sdk/lib/.keep
klu_sdk/resources/__init__.py
klu_sdk/resources/data.py
klu_sdk/resources/experiments.py
klu_sdk/resources/feedback.py
klu_sdk/resources/finetunes.py
klu_sdk/resources/models.py
klu_sdk/resources/providers.py
klu_sdk/resources/studio.py
klu_sdk/resources/actions/__init__.py
klu_sdk/resources/actions/actions.py
klu_sdk/resources/actions/context.py
klu_sdk/resources/actions/data.py
klu_sdk/resources/actions/result.py
klu_sdk/resources/actions/skills.py
klu_sdk/resources/actions/versions.py
klu_sdk/resources/apps/__init__.py
klu_sdk/resources/apps/actions.py
klu_sdk/resources/apps/apps.py
klu_sdk/resources/apps/data.py
klu_sdk/resources/apps/finetunes.py
klu_sdk/resources/apps/workflows.py
klu_sdk/resources/contexts/__init__.py
klu_sdk/resources/contexts/context_sources.py
klu_sdk/resources/contexts/contexts.py
klu_sdk/resources/contexts/documents.py
klu_sdk/resources/datasets/__init__.py
klu_sdk/resources/datasets/app.py
klu_sdk/resources/datasets/data.py
klu_sdk/resources/datasets/datasets.py
klu_sdk/resources/datasets/items.py
klu_sdk/resources/evals/__init__.py
klu_sdk/resources/evals/evals.py
klu_sdk/resources/evals/runs.py
klu_sdk/resources/evals/types.py
klu_sdk/resources/sessions/__init__.py
klu_sdk/resources/sessions/data.py
klu_sdk/resources/sessions/sessions.py
klu_sdk/resources/skills/__init__.py
klu_sdk/resources/skills/skills.py
klu_sdk/resources/skills/types.py
klu_sdk/resources/workflows/__init__.py
klu_sdk-0.1.0a1.dist-info/METADATA
klu_sdk-0.1.0a1.dist-info/WHEEL
klu_sdk-0.1.0a1.dist-info/licenses/LICENSE
klu_sdk-0.1.0a1.dist-info/RECORD
